{"difficulty": 448, "coef": 0.004479398673070138, "bias": -2.0067706055354217, "augmented": false, "detail": [{"inner_rating": 465.41093577336864, "solved": 1, "user_id": 3717, "atcoder_user_name": "mlpj56d"}, {"inner_rating": 468.4561060779956, "solved": 1, "user_id": 5452, "atcoder_user_name": "Mcpu3"}, {"inner_rating": 468.6273062730627, "solved": 1, "user_id": 5747, "atcoder_user_name": "chocopuu"}, {"inner_rating": 497.12501933973425, "solved": 1, "user_id": 5500, "atcoder_user_name": "shikaku"}, {"inner_rating": 685.0, "solved": 1, "user_id": 6033, "atcoder_user_name": "morumotto"}, {"inner_rating": 747.2290874788446, "solved": 1, "user_id": 5865, "atcoder_user_name": "Matumo"}, {"inner_rating": 791.7288707659958, "solved": 1, "user_id": 5495, "atcoder_user_name": "mine691"}, {"inner_rating": 993.979366723767, "solved": 1, "user_id": 5880, "atcoder_user_name": "cherrypi59"}, {"inner_rating": 1027.3600410286178, "solved": 1, "user_id": 394, "atcoder_user_name": "fmhr"}, {"inner_rating": 1047.9260056264663, "solved": 1, "user_id": 5631, "atcoder_user_name": "aguroshou"}, {"inner_rating": 1229.8705129249101, "solved": 1, "user_id": 1637, "atcoder_user_name": "jbyxm"}, {"inner_rating": 1241.200177702402, "solved": 1, "user_id": 5653, "atcoder_user_name": "kobaya0514"}, {"inner_rating": 1290.5445904721619, "solved": 1, "user_id": 2324, "atcoder_user_name": "nekoTheShadow"}, {"inner_rating": 1310.8627621702867, "solved": 0, "user_id": 1206, "atcoder_user_name": "ikd"}, {"inner_rating": 1311.4911097877198, "solved": 1, "user_id": 1143, "atcoder_user_name": "hamukichi"}, {"inner_rating": 1313.788484411379, "solved": 1, "user_id": 5429, "atcoder_user_name": "face4"}, {"inner_rating": 1360.2382039525114, "solved": 1, "user_id": 5451, "atcoder_user_name": "prd_xxx"}, {"inner_rating": 1388.9266630079355, "solved": 1, "user_id": 2281, "atcoder_user_name": "kuretchi"}, {"inner_rating": 1391.474360495601, "solved": 1, "user_id": 5232, "atcoder_user_name": "tatyam"}, {"inner_rating": 1402.2996065484615, "solved": 1, "user_id": 5390, "atcoder_user_name": "kerotono"}, {"inner_rating": 1477.6493862300306, "solved": 1, "user_id": 3966, "atcoder_user_name": "uwfdai"}, {"inner_rating": 1529.1071946161503, "solved": 1, "user_id": 4153, "atcoder_user_name": "SugarDragon5"}, {"inner_rating": 1539.243435797501, "solved": 1, "user_id": 1653, "atcoder_user_name": "sekiya9311"}, {"inner_rating": 1613.5910975044499, "solved": 1, "user_id": 237, "atcoder_user_name": "x20"}, {"inner_rating": 1680.570405274571, "solved": 1, "user_id": 4229, "atcoder_user_name": "RTIA1227"}, {"inner_rating": 1699.1530340449585, "solved": 1, "user_id": 2187, "atcoder_user_name": "claw88"}, {"inner_rating": 1702.4825591129804, "solved": 1, "user_id": 1946, "atcoder_user_name": "mmxsrup"}, {"inner_rating": 1714.8628067661264, "solved": 1, "user_id": 5914, "atcoder_user_name": "chocorusk"}, {"inner_rating": 1779.366937354785, "solved": 1, "user_id": 732, "atcoder_user_name": "phyllo"}, {"inner_rating": 1801.9248254935412, "solved": 1, "user_id": 5970, "atcoder_user_name": "potoooooooo"}, {"inner_rating": 1846.3503477492013, "solved": 1, "user_id": 1664, "atcoder_user_name": "fine"}, {"inner_rating": 1930.747466665995, "solved": 0, "user_id": 25, "atcoder_user_name": "nmnmnmnmnmnmnm"}, {"inner_rating": 1955.8091929590394, "solved": 1, "user_id": 3342, "atcoder_user_name": "merom686"}, {"inner_rating": 1981.036614939541, "solved": 0, "user_id": 1712, "atcoder_user_name": "paruki"}, {"inner_rating": 2030.274534129987, "solved": 1, "user_id": 2392, "atcoder_user_name": "nebukuro09"}, {"inner_rating": 2049.0969945070474, "solved": 1, "user_id": 629, "atcoder_user_name": "FF256grhy"}, {"inner_rating": 2329.0402155117126, "solved": 1, "user_id": 6953, "atcoder_user_name": "pekempey"}, {"inner_rating": 2458.127784261704, "solved": 1, "user_id": 1255, "atcoder_user_name": "kimiyuki"}, {"inner_rating": 2466.7599398874745, "solved": 1, "user_id": 233, "atcoder_user_name": "mamekin"}, {"inner_rating": 2915.3442634720705, "solved": 1, "user_id": 90, "atcoder_user_name": "kmjp"}, {"inner_rating": 2924.02596669044, "solved": 1, "user_id": 3367, "atcoder_user_name": "WA_TLE"}]}