{"difficulty": 1045, "coef": 0.004479398673070138, "bias": -4.6809716133582935, "augmented": false, "detail": [{"inner_rating": 2217.860721570425, "solved": true, "user_id": 208, "atcoder_user_name": "kzyKT"}, {"inner_rating": 2167.9890460565052, "solved": true, "user_id": 289, "atcoder_user_name": "eitaho"}, {"inner_rating": 1646.128080056336, "solved": true, "user_id": 2437, "atcoder_user_name": "olphe"}, {"inner_rating": 2532.9813022479557, "solved": true, "user_id": 333, "atcoder_user_name": "camypaper"}, {"inner_rating": 2352.771593637246, "solved": true, "user_id": 123, "atcoder_user_name": "koyumeishi"}, {"inner_rating": 2156.313488212076, "solved": true, "user_id": 844, "atcoder_user_name": "h_noson"}, {"inner_rating": 1868.9655347820078, "solved": true, "user_id": 629, "atcoder_user_name": "FF256grhy"}, {"inner_rating": 2825.0705647423997, "solved": true, "user_id": 90, "atcoder_user_name": "kmjp"}, {"inner_rating": 1775.2827150650849, "solved": true, "user_id": 1373, "atcoder_user_name": "m_buyoh"}, {"inner_rating": 1471.6973013317943, "solved": true, "user_id": 2187, "atcoder_user_name": "claw88"}, {"inner_rating": 2384.507066636374, "solved": true, "user_id": 210, "atcoder_user_name": "piroz95"}, {"inner_rating": 1533.535223714451, "solved": true, "user_id": 2138, "atcoder_user_name": "algon"}, {"inner_rating": 2527.909488814991, "solved": true, "user_id": 209, "atcoder_user_name": "kobae964"}, {"inner_rating": 2095.214653927125, "solved": true, "user_id": 726, "atcoder_user_name": "shiratty8"}, {"inner_rating": 2059.8284643041757, "solved": true, "user_id": 1282, "atcoder_user_name": "satanic0258"}, {"inner_rating": 1320.152411581021, "solved": true, "user_id": 1301, "atcoder_user_name": "ebicochineal"}, {"inner_rating": 2773.0000000000005, "solved": true, "user_id": 100, "atcoder_user_name": "chaemon"}, {"inner_rating": 1922.1278251168558, "solved": true, "user_id": 78, "atcoder_user_name": "kuuso"}, {"inner_rating": 1212.612566345829, "solved": true, "user_id": 394, "atcoder_user_name": "fmhr"}, {"inner_rating": 2510.580941074542, "solved": true, "user_id": 1195, "atcoder_user_name": "rickytheta"}, {"inner_rating": 2373.645604369553, "solved": true, "user_id": 1255, "atcoder_user_name": "kimiyuki"}, {"inner_rating": 1737.6660772573798, "solved": true, "user_id": 102, "atcoder_user_name": "hotpepsi"}, {"inner_rating": 1897.2758606706943, "solved": true, "user_id": 137, "atcoder_user_name": "threepipes_s"}, {"inner_rating": 1076.8450627226473, "solved": true, "user_id": 907, "atcoder_user_name": "naoyk1212"}, {"inner_rating": 1856.3922651933701, "solved": true, "user_id": 2600, "atcoder_user_name": "kotatsugame"}, {"inner_rating": 1621.4144538056598, "solved": false, "user_id": 1984, "atcoder_user_name": "kurenai3110"}, {"inner_rating": 2555.170744070794, "solved": true, "user_id": 6953, "atcoder_user_name": "pekempey"}, {"inner_rating": 2124.940984741424, "solved": true, "user_id": 540, "atcoder_user_name": "hirokazu1020"}, {"inner_rating": 3110.7050688815903, "solved": true, "user_id": 74, "atcoder_user_name": "uwi"}, {"inner_rating": 3006.2252862379387, "solved": true, "user_id": 2, "atcoder_user_name": "anta"}, {"inner_rating": 1822.3012503634777, "solved": true, "user_id": 69, "atcoder_user_name": "matsu7874"}, {"inner_rating": 2122.661648112538, "solved": true, "user_id": 386, "atcoder_user_name": "femto16"}, {"inner_rating": 1183.0, "solved": false, "user_id": 2792, "atcoder_user_name": "mono1977"}, {"inner_rating": 1841.272763286614, "solved": true, "user_id": 654, "atcoder_user_name": "garnacha"}, {"inner_rating": 1440.9146069019905, "solved": true, "user_id": 4323, "atcoder_user_name": "physics0523"}, {"inner_rating": 1494.8836606366726, "solved": true, "user_id": 2299, "atcoder_user_name": "tsutaj"}, {"inner_rating": 1739.8365663665263, "solved": true, "user_id": 1664, "atcoder_user_name": "fine"}, {"inner_rating": 1853.7472851237005, "solved": true, "user_id": 2422, "atcoder_user_name": "gigime"}, {"inner_rating": 2029.5813218284502, "solved": true, "user_id": 1712, "atcoder_user_name": "paruki"}, {"inner_rating": 2368.083163710381, "solved": true, "user_id": 120, "atcoder_user_name": "shimomire"}, {"inner_rating": 1008.4934269461181, "solved": false, "user_id": 1637, "atcoder_user_name": "jbyxm"}, {"inner_rating": 1879.2115420622833, "solved": true, "user_id": 2392, "atcoder_user_name": "nebukuro09"}, {"inner_rating": 1985.0312765733083, "solved": true, "user_id": 571, "atcoder_user_name": "n_knuu"}, {"inner_rating": 1729.0511273986524, "solved": true, "user_id": 432, "atcoder_user_name": "t8m8"}, {"inner_rating": 2354.6589686363773, "solved": true, "user_id": 241, "atcoder_user_name": "mayoko"}, {"inner_rating": 2180.3751195726054, "solved": true, "user_id": 555, "atcoder_user_name": "riantkb"}]}