{"difficulty": 2920, "coef": 0.004479398673070138, "bias": -13.079844125364803, "augmented": false, "detail": [{"inner_rating": 441.6226001553143, "solved": 0, "user_id": 18182, "atcoder_user_name": "VvyLw"}, {"inner_rating": 753.1578947368422, "solved": 0, "user_id": 18404, "atcoder_user_name": "anonymously"}, {"inner_rating": 864.5539478705836, "solved": 0, "user_id": 18640, "atcoder_user_name": "tipstar0125"}, {"inner_rating": 869.3435940170244, "solved": 0, "user_id": 18736, "atcoder_user_name": "i_taku"}, {"inner_rating": 908.8528561704768, "solved": 0, "user_id": 15582, "atcoder_user_name": "n_na"}, {"inner_rating": 1077.4981217044572, "solved": 0, "user_id": 18129, "atcoder_user_name": "navel_tos"}, {"inner_rating": 1127.075771675243, "solved": 0, "user_id": 17999, "atcoder_user_name": "CoCo_Japan_pan"}, {"inner_rating": 1160.1092155479857, "solved": 0, "user_id": 18534, "atcoder_user_name": "eoeo"}, {"inner_rating": 1200.9521947257851, "solved": 0, "user_id": 18530, "atcoder_user_name": "inkkk"}, {"inner_rating": 1346.3454479926993, "solved": 0, "user_id": 18627, "atcoder_user_name": "miya145592"}, {"inner_rating": 1379.5250459387184, "solved": 0, "user_id": 17955, "atcoder_user_name": "haihamabossu"}, {"inner_rating": 1452.5041906279873, "solved": 0, "user_id": 18154, "atcoder_user_name": "jabee"}, {"inner_rating": 1532.9056982139405, "solved": 0, "user_id": 10852, "atcoder_user_name": "makio93"}, {"inner_rating": 1557.2159125103792, "solved": 0, "user_id": 9606, "atcoder_user_name": "timi"}, {"inner_rating": 1600.1114341111595, "solved": 0, "user_id": 18243, "atcoder_user_name": "sgfc"}, {"inner_rating": 1604.907719252875, "solved": 0, "user_id": 16649, "atcoder_user_name": "sepa_38"}, {"inner_rating": 1606.298360537001, "solved": 0, "user_id": 12474, "atcoder_user_name": "sten"}, {"inner_rating": 1698.1304759921359, "solved": 0, "user_id": 7731, "atcoder_user_name": "ks2m"}, {"inner_rating": 1702.650886373126, "solved": 0, "user_id": 15357, "atcoder_user_name": "kabipoyo"}, {"inner_rating": 1747.6022678207516, "solved": 0, "user_id": 13681, "atcoder_user_name": "rlangevin"}, {"inner_rating": 1764.452946826827, "solved": 0, "user_id": 15746, "atcoder_user_name": "emankcin"}, {"inner_rating": 1780.1429210816248, "solved": 0, "user_id": 7289, "atcoder_user_name": "ktr216"}, {"inner_rating": 1801.574614113766, "solved": 0, "user_id": 13563, "atcoder_user_name": "joker_x"}, {"inner_rating": 1814.2370577931606, "solved": 0, "user_id": 15683, "atcoder_user_name": "wanui"}, {"inner_rating": 1887.1544595708651, "solved": 0, "user_id": 15070, "atcoder_user_name": "houren"}, {"inner_rating": 1888.9116464699227, "solved": 0, "user_id": 15770, "atcoder_user_name": "akua"}, {"inner_rating": 1906.3860540373876, "solved": 0, "user_id": 14368, "atcoder_user_name": "k1suxu"}, {"inner_rating": 1907.3684447304745, "solved": 0, "user_id": 208, "atcoder_user_name": "kzyKT"}, {"inner_rating": 1929.8547238697035, "solved": 0, "user_id": 6574, "atcoder_user_name": "titia"}, {"inner_rating": 1968.6245087850584, "solved": 0, "user_id": 9570, "atcoder_user_name": "mkawa2"}, {"inner_rating": 1979.351979461853, "solved": 0, "user_id": 9087, "atcoder_user_name": "Ricky_pon"}, {"inner_rating": 1986.3253692459334, "solved": 0, "user_id": 14510, "atcoder_user_name": "dyktr_06"}, {"inner_rating": 1996.6702975295161, "solved": 0, "user_id": 15158, "atcoder_user_name": "otoshigo"}, {"inner_rating": 2001.9135747351813, "solved": 0, "user_id": 13736, "atcoder_user_name": "aaaaaaaaaa2230"}, {"inner_rating": 2007.8417897900401, "solved": 0, "user_id": 10024, "atcoder_user_name": "pointN"}, {"inner_rating": 2019.032233750735, "solved": 0, "user_id": 13250, "atcoder_user_name": "hongrock"}, {"inner_rating": 2049.1819238295216, "solved": 0, "user_id": 16704, "atcoder_user_name": "KKT89"}, {"inner_rating": 2096.372983723135, "solved": 0, "user_id": 15874, "atcoder_user_name": "chro4896"}, {"inner_rating": 2113.8480627213626, "solved": 0, "user_id": 18080, "atcoder_user_name": "amentorimaru"}, {"inner_rating": 2135.3711620540867, "solved": 0, "user_id": 10360, "atcoder_user_name": "shobonvip"}, {"inner_rating": 2272.945167149982, "solved": 0, "user_id": 16208, "atcoder_user_name": "siganai"}, {"inner_rating": 2278.118562616121, "solved": 1, "user_id": 4746, "atcoder_user_name": "ei13333"}, {"inner_rating": 2295.8390665077363, "solved": 0, "user_id": 15072, "atcoder_user_name": "KBTIT"}, {"inner_rating": 2313.169467394164, "solved": 0, "user_id": 14450, "atcoder_user_name": "ecottea"}, {"inner_rating": 2342.9963617194135, "solved": 0, "user_id": 9323, "atcoder_user_name": "SPD_9X2"}, {"inner_rating": 2465.356894967121, "solved": 0, "user_id": 10074, "atcoder_user_name": "rniya"}, {"inner_rating": 2532.554627780885, "solved": 0, "user_id": 7172, "atcoder_user_name": "emthrm"}, {"inner_rating": 2622.7236944148485, "solved": 0, "user_id": 90, "atcoder_user_name": "kmjp"}, {"inner_rating": 2625.0242197732073, "solved": 0, "user_id": 7038, "atcoder_user_name": "leaf1415"}, {"inner_rating": 2659.2124310731338, "solved": 0, "user_id": 10535, "atcoder_user_name": "chinerist"}, {"inner_rating": 2701.378660813119, "solved": 1, "user_id": 11367, "atcoder_user_name": "tokusakurai"}, {"inner_rating": 2755.15199450893, "solved": 0, "user_id": 7896, "atcoder_user_name": "Nyaan"}, {"inner_rating": 2813.9498300794567, "solved": 1, "user_id": 2600, "atcoder_user_name": "kotatsugame"}, {"inner_rating": 2875.3167791523756, "solved": 1, "user_id": 8823, "atcoder_user_name": "maspy"}, {"inner_rating": 2973.028290516222, "solved": 1, "user_id": 13086, "atcoder_user_name": "potato167"}, {"inner_rating": 3086.9631890315036, "solved": 0, "user_id": 6298, "atcoder_user_name": "hitonanode"}, {"inner_rating": 3239.4348234967424, "solved": 0, "user_id": 11774, "atcoder_user_name": "heno239"}]}