{"difficulty": 2460, "coef": 0.004479398673070138, "bias": -11.019320735752538, "augmented": false, "detail": [{"inner_rating": 481.54673370909535, "solved": 0, "user_id": 12388, "atcoder_user_name": "DHMO"}, {"inner_rating": 538.688004478197, "solved": 0, "user_id": 14437, "atcoder_user_name": "ringo99"}, {"inner_rating": 956.7040510726213, "solved": 0, "user_id": 17999, "atcoder_user_name": "CoCo_Japan_pan"}, {"inner_rating": 1000.1091172238905, "solved": 0, "user_id": 16026, "atcoder_user_name": "floralf"}, {"inner_rating": 1163.8202371619504, "solved": 0, "user_id": 17617, "atcoder_user_name": "Sarievo"}, {"inner_rating": 1163.855346418712, "solved": 0, "user_id": 16325, "atcoder_user_name": "satama6"}, {"inner_rating": 1167.0083700338103, "solved": 0, "user_id": 17397, "atcoder_user_name": "ynm3n"}, {"inner_rating": 1182.1495486289607, "solved": 0, "user_id": 8525, "atcoder_user_name": "watarimaycry2"}, {"inner_rating": 1362.185003880444, "solved": 0, "user_id": 9606, "atcoder_user_name": "timi"}, {"inner_rating": 1512.6073217588412, "solved": 1, "user_id": 16105, "atcoder_user_name": "umimel"}, {"inner_rating": 1573.7305585087404, "solved": 0, "user_id": 11023, "atcoder_user_name": "tsugutsugu"}, {"inner_rating": 1575.4223810064907, "solved": 0, "user_id": 10825, "atcoder_user_name": "Keroru"}, {"inner_rating": 1582.8621095457195, "solved": 0, "user_id": 10876, "atcoder_user_name": "umezo"}, {"inner_rating": 1591.1583841420927, "solved": 0, "user_id": 15541, "atcoder_user_name": "flygon"}, {"inner_rating": 1645.3782682987767, "solved": 0, "user_id": 13681, "atcoder_user_name": "rlangevin"}, {"inner_rating": 1664.146710352016, "solved": 0, "user_id": 15354, "atcoder_user_name": "ripity"}, {"inner_rating": 1669.3773965823714, "solved": 0, "user_id": 16065, "atcoder_user_name": "gucci0512"}, {"inner_rating": 1721.4844030743682, "solved": 0, "user_id": 6958, "atcoder_user_name": "siro53"}, {"inner_rating": 1723.1997350987397, "solved": 0, "user_id": 15746, "atcoder_user_name": "emankcin"}, {"inner_rating": 1734.8261478856546, "solved": 0, "user_id": 15770, "atcoder_user_name": "akua"}, {"inner_rating": 1739.6446587555752, "solved": 0, "user_id": 15070, "atcoder_user_name": "houren"}, {"inner_rating": 1766.3223298893295, "solved": 0, "user_id": 9888, "atcoder_user_name": "ttkkggww"}, {"inner_rating": 1771.476018006832, "solved": 0, "user_id": 14254, "atcoder_user_name": "Navier_Boltzmann"}, {"inner_rating": 1810.0316657009132, "solved": 0, "user_id": 15357, "atcoder_user_name": "kabipoyo"}, {"inner_rating": 1822.9143984546631, "solved": 0, "user_id": 14382, "atcoder_user_name": "mn_7545"}, {"inner_rating": 1829.2297232578312, "solved": 0, "user_id": 15683, "atcoder_user_name": "wanui"}, {"inner_rating": 1829.549911909512, "solved": 0, "user_id": 14368, "atcoder_user_name": "k1suxu"}, {"inner_rating": 1837.2564203209, "solved": 0, "user_id": 11268, "atcoder_user_name": "AngrySadEight"}, {"inner_rating": 1845.8387667744805, "solved": 0, "user_id": 7289, "atcoder_user_name": "ktr216"}, {"inner_rating": 1865.9318900360352, "solved": 0, "user_id": 9419, "atcoder_user_name": "abb"}, {"inner_rating": 1881.1433439048114, "solved": 0, "user_id": 14227, "atcoder_user_name": "Shirotsume"}, {"inner_rating": 1916.0896713256718, "solved": 0, "user_id": 16054, "atcoder_user_name": "Nzt3"}, {"inner_rating": 1916.8054355627332, "solved": 0, "user_id": 14510, "atcoder_user_name": "dyktr_06"}, {"inner_rating": 1916.9829129967413, "solved": 0, "user_id": 9113, "atcoder_user_name": "gyouzasushi"}, {"inner_rating": 1938.7324306189362, "solved": 0, "user_id": 16185, "atcoder_user_name": "yfuka86"}, {"inner_rating": 1949.1254901225736, "solved": 0, "user_id": 208, "atcoder_user_name": "kzyKT"}, {"inner_rating": 1952.3540873900427, "solved": 0, "user_id": 6574, "atcoder_user_name": "titia"}, {"inner_rating": 1965.3641681365086, "solved": 0, "user_id": 6913, "atcoder_user_name": "ir_1st_vil"}, {"inner_rating": 1973.0935313572502, "solved": 0, "user_id": 17752, "atcoder_user_name": "tktk_snsn"}, {"inner_rating": 1976.6121623567892, "solved": 0, "user_id": 13452, "atcoder_user_name": "tassei903"}, {"inner_rating": 1984.8783370570525, "solved": 0, "user_id": 1150, "atcoder_user_name": "hiromi_ayase"}, {"inner_rating": 1993.5676101923086, "solved": 0, "user_id": 14969, "atcoder_user_name": "ruthen71"}, {"inner_rating": 2001.9135747351813, "solved": 0, "user_id": 13736, "atcoder_user_name": "aaaaaaaaaa2230"}, {"inner_rating": 2013.414035491628, "solved": 0, "user_id": 16704, "atcoder_user_name": "KKT89"}, {"inner_rating": 2020.5769543951399, "solved": 0, "user_id": 11274, "atcoder_user_name": "Kazu1998k"}, {"inner_rating": 2039.4105431798134, "solved": 0, "user_id": 15874, "atcoder_user_name": "chro4896"}, {"inner_rating": 2051.188786979835, "solved": 0, "user_id": 10224, "atcoder_user_name": "stoq"}, {"inner_rating": 2053.7062423240727, "solved": 1, "user_id": 10360, "atcoder_user_name": "shobonvip"}, {"inner_rating": 2059.5701980235153, "solved": 0, "user_id": 11797, "atcoder_user_name": "sounansya"}, {"inner_rating": 2062.9844749987487, "solved": 0, "user_id": 7522, "atcoder_user_name": "niuez"}, {"inner_rating": 2066.0782064580007, "solved": 0, "user_id": 9570, "atcoder_user_name": "mkawa2"}, {"inner_rating": 2151.441427320152, "solved": 0, "user_id": 8587, "atcoder_user_name": "hir35"}, {"inner_rating": 2153.003034763082, "solved": 1, "user_id": 9410, "atcoder_user_name": "minato_"}, {"inner_rating": 2164.5769437703325, "solved": 0, "user_id": 17913, "atcoder_user_name": "rabimea"}, {"inner_rating": 2173.4735488897372, "solved": 0, "user_id": 3220, "atcoder_user_name": "pachicobue"}, {"inner_rating": 2181.5831868558075, "solved": 0, "user_id": 16208, "atcoder_user_name": "siganai"}, {"inner_rating": 2187.1755431087527, "solved": 0, "user_id": 10411, "atcoder_user_name": "hamamu"}, {"inner_rating": 2295.8390665077363, "solved": 0, "user_id": 15072, "atcoder_user_name": "KBTIT"}, {"inner_rating": 2348.708049229132, "solved": 0, "user_id": 14450, "atcoder_user_name": "ecottea"}, {"inner_rating": 2398.4085873920017, "solved": 1, "user_id": 9216, "atcoder_user_name": "haruki_K"}, {"inner_rating": 2430.947377871806, "solved": 1, "user_id": 10074, "atcoder_user_name": "rniya"}, {"inner_rating": 2452.6238130457186, "solved": 1, "user_id": 7038, "atcoder_user_name": "leaf1415"}, {"inner_rating": 2490.2933392777045, "solved": 1, "user_id": 7821, "atcoder_user_name": "ttttan"}, {"inner_rating": 2511.4397332281364, "solved": 1, "user_id": 7172, "atcoder_user_name": "emthrm"}, {"inner_rating": 2653.443226374485, "solved": 0, "user_id": 90, "atcoder_user_name": "kmjp"}, {"inner_rating": 2751.2774035199805, "solved": 1, "user_id": 555, "atcoder_user_name": "riantkb"}, {"inner_rating": 2755.15199450893, "solved": 1, "user_id": 7896, "atcoder_user_name": "Nyaan"}, {"inner_rating": 2783.3700518623987, "solved": 1, "user_id": 8204, "atcoder_user_name": "Rubikun"}, {"inner_rating": 2788.094619893179, "solved": 1, "user_id": 8564, "atcoder_user_name": "tute7627"}, {"inner_rating": 2875.3167791523756, "solved": 1, "user_id": 8823, "atcoder_user_name": "maspy"}, {"inner_rating": 2898.266403111546, "solved": 1, "user_id": 12532, "atcoder_user_name": "Nachia"}, {"inner_rating": 2955.4610991991585, "solved": 1, "user_id": 10449, "atcoder_user_name": "SSRS"}, {"inner_rating": 3075.1968081543205, "solved": 0, "user_id": 5232, "atcoder_user_name": "tatyam"}, {"inner_rating": 3122.203357385301, "solved": 1, "user_id": 174, "atcoder_user_name": "hos_lyric"}, {"inner_rating": 3301.7496626186394, "solved": 1, "user_id": 18016, "atcoder_user_name": "jiangly"}]}